can_explorer/__init__.py
can_explorer/__main__.py
can_explorer/app.py
can_explorer/configs.py
can_explorer/controllers.py
can_explorer/models.py
can_explorer/plotting.py
can_explorer/tags.py
can_explorer/ui_builder.py
can_explorer/views.py
can_explorer/resources/Inter-Medium.ttf
can_explorer/resources/NotoSerifCJKjp-Medium.otf
can_explorer/resources/__init__.py
can_explorer/resources/demo.py
can_explorer-0.2.2.dist-info/METADATA
can_explorer-0.2.2.dist-info/WHEEL
can_explorer-0.2.2.dist-info/entry_points.txt
can_explorer-0.2.2.dist-info/licenses/LICENSE
can_explorer-0.2.2.dist-info/RECORD
