Metadata-Version: 2.4
Name: can-explorer
Version: 0.2.2
Summary: Visualize CAN bus payloads in real time
Project-URL: repository, https://github.com/tbruno25/can-explorer
Author-email: TJ <tbruno25@gmail.com>
License-File: LICENSE
Keywords: bus,can,can_bus,canbus,dbc
Classifier: License :: OSI Approved :: GNU General Public License v3 (GPLv3)
Classifier: Operating System :: OS Independent
Classifier: Programming Language :: Python :: 3
Classifier: Programming Language :: Python :: 3.10
Classifier: Programming Language :: Python :: 3.11
Classifier: Programming Language :: Python :: 3.12
Requires-Python: >=3.10
Requires-Dist: dearpygui-ext<2.0.0,>=0.9.0
Requires-Dist: dearpygui<2.0.0,>=1.9.0
Requires-Dist: pyserial>=3.5
Requires-Dist: python-can>=4.0.0
Provides-Extra: dev
Requires-Dist: msvc-runtime; (platform_system == 'Windows') and extra == 'dev'
Requires-Dist: opencv-python>=4.10.0.84; extra == 'dev'
Requires-Dist: pillow>=10.4.0; extra == 'dev'
Requires-Dist: pytest-dpg>=0.1.5; extra == 'dev'
Requires-Dist: pytest>=8.3.2; extra == 'dev'
